pword/__init__.py
pword/word.py
sketchpy/__init__.py
sketchpy/canvas.py
sketchpy/library.py
pword-0.0.1.dist-info/LICENSE
pword-0.0.1.dist-info/METADATA
pword-0.0.1.dist-info/WHEEL
pword-0.0.1.dist-info/top_level.txt
pword-0.0.1.dist-info/RECORD
