Metadata-Version: 2.1
Name: pword
Version: 0.0.1
Summary: nope
Home-page: UNKNOWN
Author: anonymos
Author-email: dontknow007@gmail.com
License: UNKNOWN
Platform: UNKNOWN
Classifier: Development Status :: 1 - Planning
Classifier: Intended Audience :: Developers
Classifier: Programming Language :: Python :: 3
Classifier: Operating System :: Unix
Classifier: Operating System :: MacOS :: MacOS X
Classifier: Operating System :: Microsoft :: Windows
Requires-Dist: requests
